PCILib/PCIhashLib.py
PCILib/PCIosLib.py
PCILib/__init__.py
PCILib/PCImathLib/__init__.py
PCILib/PCImathLib/analysis/__init__.py
PCILib/PCImathLib/discrete/__init__.py
PCILib/PCImathLib/stat/__init__.py
PCILib/core/__init__.py
PCILib/core/bit.py
PCILib-0.0.3.dist-info/LICENSE.txt
PCILib-0.0.3.dist-info/METADATA
PCILib-0.0.3.dist-info/WHEEL
PCILib-0.0.3.dist-info/top_level.txt
PCILib-0.0.3.dist-info/RECORD
